MRcalib/__init__.py
MRcalib/__main__.py
MagnetoResistance_tool-0.0.4.dist-info/LICENCE
MagnetoResistance_tool-0.0.4.dist-info/METADATA
MagnetoResistance_tool-0.0.4.dist-info/WHEEL
MagnetoResistance_tool-0.0.4.dist-info/entry_points.txt
MagnetoResistance_tool-0.0.4.dist-info/top_level.txt
MagnetoResistance_tool-0.0.4.dist-info/RECORD
