Metadata-Version: 2.1
Name: MagnetoResistance-tool
Version: 0.0.4
Summary: Tool to create calibration matrix allowing to correct for magneto-resistance in resisitive sensors.
Author: Nowa Ammerlaan
Author-email: <nowa.ammerlaan@ru.nl>
Maintainer: Nowa Ammerlaan
Maintainer-email: <nowa.ammerlaan@ru.nl>
License: GPL-3.0-or-later
Project-URL: homepage, https://gitlab.science.ru.nl/hfml/MRcalib
Project-URL: repository, https://gitlab.science.ru.nl/hfml/MRcalib
Keywords: magneto-resistance
Requires-Python: >=3.10
License-File: LICENCE
Requires-Dist: numpy
Requires-Dist: pandas
Provides-Extra: plot
Requires-Dist: matplotlib; extra == "plot"
